django_inngest/__init__.py
django_inngest/client.py
django_inngest/defaults.py
django_inngest/discovery.py
django_inngest/urls.py
django_inngest-0.0.7.dist-info/METADATA
django_inngest-0.0.7.dist-info/WHEEL
django_inngest-0.0.7.dist-info/top_level.txt
django_inngest-0.0.7.dist-info/RECORD
